{
  "entry": "server.js",
  "files": {
    "components/characters-character-preview.js": "components/characters-character-preview.js",
    "components/characters-list.js": "components/characters-list.js",
    "components/episodes-list.js": "components/episodes-list.js",
    "components/episodes-preview.js": "components/episodes-preview.js",
    "components/locations-list-item.js": "components/locations-list-item.js",
    "components/locations-list.js": "components/locations-list.js",
    "components/locations-location-one-character.js": "components/locations-location-one-character.js",
    "components/system-header.js": "components/system-header.js",
    "components/system-logo.js": "components/system-logo.js",
    "pages/about/index.js": "pages/about/index.js",
    "pages/characters/_id/index.js": "pages/characters/_id/index.js",
    "pages/characters/index.js": "pages/characters/index.js",
    "pages/episodes/_id/index.js": "pages/episodes/_id/index.js",
    "pages/episodes/index.js": "pages/episodes/index.js",
    "pages/index.js": "pages/index.js",
    "pages/locations/_id/index.js": "pages/locations/_id/index.js",
    "pages/locations/index.js": "pages/locations/index.js",
    "server.js": "server.js"
  },
  "maps": {
    "components/characters-character-preview.js": "components/characters-character-preview.js.map",
    "components/characters-list.js": "components/characters-list.js.map",
    "components/episodes-list.js": "components/episodes-list.js.map",
    "components/episodes-preview.js": "components/episodes-preview.js.map",
    "components/locations-list-item.js": "components/locations-list-item.js.map",
    "components/locations-list.js": "components/locations-list.js.map",
    "components/locations-location-one-character.js": "components/locations-location-one-character.js.map",
    "components/system-header.js": "components/system-header.js.map",
    "components/system-logo.js": "components/system-logo.js.map",
    "pages/about/index.js": "pages/about/index.js.map",
    "pages/characters/_id/index.js": "pages/characters/_id/index.js.map",
    "pages/characters/index.js": "pages/characters/index.js.map",
    "pages/episodes/_id/index.js": "pages/episodes/_id/index.js.map",
    "pages/episodes/index.js": "pages/episodes/index.js.map",
    "pages/index.js": "pages/index.js.map",
    "pages/locations/_id/index.js": "pages/locations/_id/index.js.map",
    "pages/locations/index.js": "pages/locations/index.js.map",
    "server.js": "server.js.map"
  }
}